[
  {
    "student_id": "Baseline 1",
    "submission_time": "",
    "levels": {
      "SeekAndSlayLevel0-v0": {
        "ammo": 0,
        "health": 0,
        "kills": 23
      },
      "SeekAndSlayLevel1_6-v0": {
        "ammo": 0,
        "health": 0,
        "kills": 7
      }
    },
    "audit": {
      "run_url": ""
    }
  },
  {
    "student_id": "Baseline 2",
    "submission_time": "",
    "levels": {
      "SeekAndSlayLevel0-v0": {
        "ammo": 0,
        "health": 0,
        "kills": 23
      },
      "SeekAndSlayLevel1_6-v0": {
        "ammo": 0,
        "health": 0,
        "kills": 9
      },
      "SeekAndSlayLevel3_1-v0": {
        "ammo": 0,
        "health": 0,
        "kills": 6
      }
    },
    "audit": {
      "run_url": ""
    }
  },
  {
    "student_id": "Baseline 3",
    "submission_time": "",
    "levels": {
      "SeekAndSlayLevel0-v0": {
        "ammo": 0,
        "health": 0,
        "kills": 20
      },
      "SeekAndSlayLevel1_6-v0": {
        "ammo": 0,
        "health": 0,
        "kills": 12
      },
      "SeekAndSlayLevel3_1-v0": {
        "ammo": 0,
        "health": 0,
        "kills": 10
      },
      "SeekAndSlayLevel2_3-v0": {
        "ammo": 0,
        "health": 0,
        "kills": 7
      }
    },
    "audit": {
      "run_url": ""
    }
  },
  {
    "student_id": "b11705007",
    "submission_time": "2026-04-14T07:05:39.804502+00:00",
    "levels": {
      "SeekAndSlayLevel0-v0": {
        "ammo": 60,
        "health": 100,
        "kills": 29
      },
      "SeekAndSlayLevel1_6-v0": {
        "ammo": 88,
        "health": 10,
        "kills": 13
      },
      "SeekAndSlayLevel2_3-v0": {
        "ammo": 78,
        "health": 5,
        "kills": 10
      },
      "SeekAndSlayLevel3_1-v0": {
        "ammo": 80,
        "health": 43,
        "kills": 13
      },
      "SeekAndSlayLevel4-v0": {
        "ammo": 66,
        "health": 46,
        "kills": 24
      }
    },
    "audit": {
      "run_url": "https://github.com/ntu-drl-2026-spring-hw3/hw3-2-Markbbbb/actions/runs/24224339386"
    }
  },
  {
    "student_id": "112582009",
    "submission_time": "2026-04-14T07:06:52.767421+00:00",
    "levels": {
      "SeekAndSlayLevel0-v0": {
        "ammo": 85,
        "health": 100,
        "kills": 25
      },
      "SeekAndSlayLevel1_6-v0": {
        "ammo": 76,
        "health": 30,
        "kills": 18
      },
      "SeekAndSlayLevel2_3-v0": {
        "ammo": 77,
        "health": 8,
        "kills": 14
      },
      "SeekAndSlayLevel3_1-v0": {
        "ammo": 79,
        "health": 25,
        "kills": 21
      },
      "SeekAndSlayLevel4-v0": {
        "ammo": 44,
        "health": 40,
        "kills": 16
      }
    },
    "audit": {
      "run_url": "https://github.com/ntu-drl-2026-spring-hw3/hw3-2-cghaocg/actions/runs/24328143075"
    }
  },
  {
    "student_id": "b10611035",
    "submission_time": "2026-04-14T07:07:17.838943+00:00",
    "levels": {
      "SeekAndSlayLevel0-v0": {
        "ammo": 69,
        "health": 90.4,
        "kills": 3.6
      }
    },
    "audit": {
      "run_url": "https://github.com/ntu-drl-2026-spring-hw3/hw3-2-wkh1267/actions/runs/24307488591"
    }
  },
  {
    "student_id": "b12902131",
    "submission_time": "2026-04-14T07:08:17.612531+00:00",
    "levels": {
      "SeekAndSlayLevel0-v0": {
        "ammo": 65,
        "health": 100,
        "kills": 33
      },
      "SeekAndSlayLevel1_6-v0": {
        "ammo": 63,
        "health": 64,
        "kills": 17
      },
      "SeekAndSlayLevel2_3-v0": {
        "ammo": 66,
        "health": 50,
        "kills": 22
      },
      "SeekAndSlayLevel3_1-v0": {
        "ammo": 45,
        "health": 73,
        "kills": 18
      },
      "SeekAndSlayLevel4-v0": {
        "ammo": 26,
        "health": 8,
        "kills": 11
      }
    },
    "audit": {
      "run_url": "https://github.com/ntu-drl-2026-spring-hw3/hw3-2-sinkboy-chen/actions/runs/24379592326"
    }
  },
  {
    "student_id": "r14946014",
    "submission_time": "2026-04-14T07:08:43.004473+00:00",
    "levels": {
      "SeekAndSlayLevel0-v0": {
        "ammo": 69,
        "health": 90.4,
        "kills": 3.6
      }
    },
    "audit": {
      "run_url": "https://github.com/ntu-drl-2026-spring-hw3/hw3-2-dennnnnnnnny-2/actions/runs/24259962911"
    }
  },
  {
    "student_id": "b12901071",
    "submission_time": "2026-04-14T07:09:46.575175+00:00",
    "levels": {
      "SeekAndSlayLevel0-v0": {
        "ammo": 73,
        "health": 100,
        "kills": 30
      },
      "SeekAndSlayLevel1_6-v0": {
        "ammo": 55,
        "health": 55,
        "kills": 18
      },
      "SeekAndSlayLevel2_3-v0": {
        "ammo": 88,
        "health": 55,
        "kills": 11
      },
      "SeekAndSlayLevel3_1-v0": {
        "ammo": 79,
        "health": 30,
        "kills": 17
      },
      "SeekAndSlayLevel4-v0": {
        "ammo": 68,
        "health": 4,
        "kills": 16
      }
    },
    "audit": {
      "run_url": "https://github.com/ntu-drl-2026-spring-hw3/hw3-2-estherhan1/actions/runs/24310819338"
    }
  },
  {
    "student_id": "t14902120",
    "submission_time": "2026-04-14T07:10:43.332897+00:00",
    "levels": {
      "SeekAndSlayLevel0-v0": {
        "ammo": 87,
        "health": 100,
        "kills": 34
      },
      "SeekAndSlayLevel1_6-v0": {
        "ammo": 86,
        "health": 82,
        "kills": 17
      },
      "SeekAndSlayLevel2_3-v0": {
        "ammo": 87,
        "health": 37,
        "kills": 19
      },
      "SeekAndSlayLevel3_1-v0": {
        "ammo": 86,
        "health": 7,
        "kills": 18
      },
      "SeekAndSlayLevel4-v0": {
        "ammo": 29,
        "health": 16,
        "kills": 15
      }
    },
    "audit": {
      "run_url": "https://github.com/ntu-drl-2026-spring-hw3/hw3-2-UG0303-1/actions/runs/24284914175"
    }
  },
  {
    "student_id": "b12901091",
    "submission_time": "2026-04-14T07:11:39.831503+00:00",
    "levels": {
      "SeekAndSlayLevel0-v0": {
        "ammo": 75,
        "health": 100,
        "kills": 18
      },
      "SeekAndSlayLevel1_6-v0": {
        "ammo": 57,
        "health": 7,
        "kills": 8
      }
    },
    "audit": {
      "run_url": "https://github.com/ntu-drl-2026-spring-hw3/hw3-2-beyond1125-1/actions/runs/24286808454"
    }
  },
  {
    "student_id": "r14922a11",
    "submission_time": "2026-04-14T07:12:36.902940+00:00",
    "levels": {
      "SeekAndSlayLevel0-v0": {
        "ammo": 87,
        "health": 100,
        "kills": 29
      },
      "SeekAndSlayLevel1_6-v0": {
        "ammo": 87,
        "health": 40,
        "kills": 16
      },
      "SeekAndSlayLevel2_3-v0": {
        "ammo": 89,
        "health": 16,
        "kills": 13
      },
      "SeekAndSlayLevel3_1-v0": {
        "ammo": 63,
        "health": 5,
        "kills": 11
      },
      "SeekAndSlayLevel4-v0": {
        "ammo": 69,
        "health": 2,
        "kills": 19
      }
    },
    "audit": {
      "run_url": "https://github.com/ntu-drl-2026-spring-hw3/hw3-2-qwaszxallen-2/actions/runs/24132373400"
    }
  },
  {
    "student_id": "b12902003",
    "submission_time": "2026-04-14T07:13:01.363764+00:00",
    "levels": {
      "SeekAndSlayLevel0-v0": {
        "ammo": 69,
        "health": 90.4,
        "kills": 3.6
      }
    },
    "audit": {
      "run_url": "https://github.com/ntu-drl-2026-spring-hw3/hw3-2-fxck2/actions/runs/24081714060"
    }
  },
  {
    "student_id": "r13521617",
    "submission_time": "2026-04-14T07:14:08.703180+00:00",
    "levels": {
      "SeekAndSlayLevel0-v0": {
        "ammo": 77,
        "health": 100,
        "kills": 31
      },
      "SeekAndSlayLevel1_6-v0": {
        "ammo": 72,
        "health": 85,
        "kills": 15
      },
      "SeekAndSlayLevel2_3-v0": {
        "ammo": 74,
        "health": 28,
        "kills": 13
      },
      "SeekAndSlayLevel3_1-v0": {
        "ammo": 71,
        "health": 44,
        "kills": 13
      },
      "SeekAndSlayLevel4-v0": {
        "ammo": 0,
        "health": 100,
        "kills": 0
      }
    },
    "audit": {
      "run_url": "https://github.com/ntu-drl-2026-spring-hw3/hw3-2-YungIChang517/actions/runs/24306605357"
    }
  },
  {
    "student_id": "b12902151",
    "submission_time": "2026-04-14T07:15:07.765596+00:00",
    "levels": {
      "SeekAndSlayLevel0-v0": {
        "ammo": 83,
        "health": 100,
        "kills": 37
      },
      "SeekAndSlayLevel1_6-v0": {
        "ammo": 84,
        "health": 70,
        "kills": 20
      },
      "SeekAndSlayLevel2_3-v0": {
        "ammo": 84,
        "health": 85,
        "kills": 20
      },
      "SeekAndSlayLevel3_1-v0": {
        "ammo": 83,
        "health": 64,
        "kills": 22
      },
      "SeekAndSlayLevel4-v0": {
        "ammo": 85,
        "health": 7,
        "kills": 39
      }
    },
    "audit": {
      "run_url": "https://github.com/ntu-drl-2026-spring-hw3/hw3-2-Ching367436-1/actions/runs/24283654589"
    }
  },
  {
    "student_id": "t14902154",
    "submission_time": "2026-04-14T07:16:05.601745+00:00",
    "levels": {
      "SeekAndSlayLevel0-v0": {
        "ammo": 81,
        "health": 100,
        "kills": 30
      },
      "SeekAndSlayLevel1_6-v0": {
        "ammo": 78,
        "health": 6,
        "kills": 14
      },
      "SeekAndSlayLevel2_3-v0": {
        "ammo": 47,
        "health": 2,
        "kills": 4
      },
      "SeekAndSlayLevel3_1-v0": {
        "ammo": 77,
        "health": 4,
        "kills": 12
      }
    },
    "audit": {
      "run_url": "https://github.com/ntu-drl-2026-spring-hw3/hw3-2-lcjconte-2/actions/runs/24330854743"
    }
  },
  {
    "student_id": "b11902171",
    "submission_time": "2026-04-14T07:17:08.961642+00:00",
    "levels": {
      "SeekAndSlayLevel0-v0": {
        "ammo": 81,
        "health": 100,
        "kills": 34
      },
      "SeekAndSlayLevel1_6-v0": {
        "ammo": 74,
        "health": 43,
        "kills": 17
      },
      "SeekAndSlayLevel2_3-v0": {
        "ammo": 76,
        "health": 52,
        "kills": 19
      },
      "SeekAndSlayLevel3_1-v0": {
        "ammo": 78,
        "health": 32,
        "kills": 19
      },
      "SeekAndSlayLevel4-v0": {
        "ammo": 45,
        "health": 10,
        "kills": 19
      }
    },
    "audit": {
      "run_url": "https://github.com/ntu-drl-2026-spring-hw3/hw3-2-KuoAnd/actions/runs/24379066199"
    }
  },
  {
    "student_id": "b14902068",
    "submission_time": "2026-04-14T07:17:32.941951+00:00",
    "levels": {
      "SeekAndSlayLevel0-v0": {
        "ammo": 69,
        "health": 90.4,
        "kills": 3.6
      }
    },
    "audit": {
      "run_url": "https://github.com/ntu-drl-2026-spring-hw3/hw3-2-b14902068/actions/runs/24132139442"
    }
  },
  {
    "student_id": "b11705048",
    "submission_time": "2026-04-14T07:18:36.043350+00:00",
    "levels": {
      "SeekAndSlayLevel0-v0": {
        "ammo": 89,
        "health": 100,
        "kills": 19
      },
      "SeekAndSlayLevel1_6-v0": {
        "ammo": 89,
        "health": 58,
        "kills": 10
      },
      "SeekAndSlayLevel2_3-v0": {
        "ammo": 88,
        "health": 10,
        "kills": 15
      },
      "SeekAndSlayLevel3_1-v0": {
        "ammo": 62,
        "health": 1,
        "kills": 13
      },
      "SeekAndSlayLevel4-v0": {
        "ammo": 83,
        "health": 16,
        "kills": 31
      }
    },
    "audit": {
      "run_url": "https://github.com/ntu-drl-2026-spring-hw3/hw3-2-jaylin0418/actions/runs/24132949105"
    }
  },
  {
    "student_id": "a14922120",
    "submission_time": "2026-04-14T07:19:46.594991+00:00",
    "levels": {
      "SeekAndSlayLevel0-v0": {
        "ammo": 88,
        "health": 100,
        "kills": 26
      },
      "SeekAndSlayLevel1_6-v0": {
        "ammo": 87,
        "health": 46,
        "kills": 15
      },
      "SeekAndSlayLevel2_3-v0": {
        "ammo": 86,
        "health": 91,
        "kills": 12
      },
      "SeekAndSlayLevel3_1-v0": {
        "ammo": 88,
        "health": 45,
        "kills": 15
      },
      "SeekAndSlayLevel4-v0": {
        "ammo": 51,
        "health": 22,
        "kills": 15
      }
    },
    "audit": {
      "run_url": "https://github.com/ntu-drl-2026-spring-hw3/hw3-2-samrauh-1/actions/runs/24174998532"
    }
  },
  {
    "student_id": "r14944015",
    "submission_time": "2026-04-14T07:20:51.519917+00:00",
    "levels": {
      "SeekAndSlayLevel0-v0": {
        "ammo": 85,
        "health": 100,
        "kills": 25
      },
      "SeekAndSlayLevel1_6-v0": {
        "ammo": 82,
        "health": 64,
        "kills": 13
      },
      "SeekAndSlayLevel2_3-v0": {
        "ammo": 78,
        "health": 40,
        "kills": 21
      },
      "SeekAndSlayLevel3_1-v0": {
        "ammo": 69,
        "health": 16,
        "kills": 17
      },
      "SeekAndSlayLevel4-v0": {
        "ammo": 22,
        "health": 34,
        "kills": 7
      }
    },
    "audit": {
      "run_url": "https://github.com/ntu-drl-2026-spring-hw3/hw3-2-Paul1336-1/actions/runs/24349252978"
    }
  },
  {
    "student_id": "r12323023",
    "submission_time": "2026-04-14T07:21:17.433401+00:00",
    "levels": {
      "SeekAndSlayLevel0-v0": {
        "ammo": 69,
        "health": 90.4,
        "kills": 3.6
      }
    },
    "audit": {
      "run_url": "https://github.com/ntu-drl-2026-spring-hw3/hw3-2-jingwu2001/actions/runs/24312118394"
    }
  },
  {
    "student_id": "r13521234",
    "submission_time": "2026-04-14T07:22:32.021003+00:00",
    "levels": {
      "SeekAndSlayLevel0-v0": {
        "ammo": 76,
        "health": 100,
        "kills": 21
      },
      "SeekAndSlayLevel1_6-v0": {
        "ammo": 81,
        "health": 49,
        "kills": 11
      },
      "SeekAndSlayLevel2_3-v0": {
        "ammo": 84,
        "health": 73,
        "kills": 10
      },
      "SeekAndSlayLevel3_1-v0": {
        "ammo": 80,
        "health": 7,
        "kills": 15
      },
      "SeekAndSlayLevel4-v0": {
        "ammo": 22,
        "health": 15,
        "kills": 9
      }
    },
    "audit": {
      "run_url": "https://github.com/ntu-drl-2026-spring-hw3/hw3-2-Waynelee9527/actions/runs/24292992308"
    }
  }
]
